escore/__init__.py
escore/cli.py
escore/escore.py
escore-0.1.0.dist-info/DESCRIPTION.rst
escore-0.1.0.dist-info/METADATA
escore-0.1.0.dist-info/RECORD
escore-0.1.0.dist-info/WHEEL
escore-0.1.0.dist-info/entry_points.txt
escore-0.1.0.dist-info/metadata.json
escore-0.1.0.dist-info/top_level.txt
