Metadata-Version: 2.0
Name: escore
Version: 0.1.0
Summary: Python SDK for the VMware vSphere API that allows you to manage ESX, ESXi, and vCenter, based on pyVmomi.
Home-page: https://github.com/antonputra/escore
Author: Anton Putra
Author-email: antonputra@icloud.com
License: Apache Software License 2.0
Keywords: vcenter esx vsphere pyvmomi escore
Platform: UNKNOWN
Classifier: Development Status :: 3 - Alpha
Classifier: Intended Audience :: Developers
Classifier: Intended Audience :: Information Technology
Classifier: Intended Audience :: System Administrators
Classifier: License :: OSI Approved :: Apache Software License
Classifier: Programming Language :: Python :: 2
Classifier: Programming Language :: Python :: 2.7
Classifier: Programming Language :: Python :: 3
Classifier: Programming Language :: Python :: 3.3
Classifier: Programming Language :: Python :: 3.4
Classifier: Programming Language :: Python :: 3.5
Classifier: Topic :: Software Development :: Build Tools
Classifier: Topic :: Software Development :: Libraries :: Python Modules
Classifier: Topic :: System :: Distributed Computing
Classifier: Operating System :: Microsoft :: Windows
Classifier: Operating System :: POSIX
Classifier: Operating System :: Unix
Classifier: Operating System :: MacOS
Requires-Dist: Click (>=6.0)
